{
  "map_id": 1,
  "map_name": "Map1",
  "map_mode": "Mode1",
  "Blue": {
    "name": "Blue",
    "is_win": 1,
    "score": 2,
    "players": [
      {
        "name": "Player1",
        "uid": 1,
        "hero": {
          "name": "Hero1",
          "uid": 1
        },
        "k": 5,
        "d": 3,
        "a": 10,
        "damage": 20000,
        "damage_taken": 15000,
        "heal": 5000,
        "hit": 0.392,
        "last_kills": 150,
        "head_kill": 2,
        "solo_kill": 1,
        "is_mvp": 0,
        "is_svp": 0
      },
      {
        "name": "Player2",
        "uid": 2,
        "hero": {
          "name": "Hero2",
          "uid": 2
        },
        "k": 5,
        "d": 3,
        "a": 10,
        "damage": 20000,
        "damage_taken": 15000,
        "heal": 5000,
        "hit": 0.392,
        "last_kills": 150,
        "head_kill": 2,
        "solo_kill": 1,
        "is_mvp": 0,
        "is_svp": 1
      }
    ]
  },
  "Red": {
    "name": "Red",
    "is_win": 1,
    "score": 2,
    "players": [
      {
        "name": "Player3",
        "uid": 3,
        "hero": {
          "name": "Hero3",
          "uid": 3
        },
        "k": 5,
        "d": 3,
        "a": 10,
        "damage": 20000,
        "damage_taken": 15000,
        "heal": 5000,
        "hit": 0.392,
        "last_kills": 150,
        "head_kill": 2,
        "solo_kill": 1,
        "is_mvp": 1,
        "is_svp": 0
      },
      {
        "name": "Player4",
        "uid": 4,
        "hero": {
          "name": "Hero4",
          "uid": 4
        },
        "k": 5,
        "d": 3,
        "a": 10,
        "damage": 20000,
        "damage_taken": 15000,
        "heal": 5000,
        "hit": 0.392,
        "last_kills": 150,
        "head_kill": 2,
        "solo_kill": 1,
        "is_mvp": 0,
        "is_svp": 0
      }
    ]
  },
  "Draft": [
    {
      "operate_type": 0,
      "battle_side": 1,
      "hero_id": 1011,
      "round_index": 0,
      "ban_pick_num": 1,
      "is_only_one_side": true,
      "mode_order_type": 1,
      "votes": [],
      "conf_id": 2004,
      "camp": 2
    },
    {
      "operate_type": 0,
      "battle_side": 0,
      "hero_id": 1021,
      "round_index": 0,
      "ban_pick_num": 1,
      "is_only_one_side": true,
      "mode_order_type": 1,
      "votes": [],
      "conf_id": 2004,
      "camp": 1
    },
    {
      "operate_type": 1,
      "battle_side": 0,
      "hero_id": 1051,
      "round_index": 1,
      "ban_pick_num": 1,
      "is_only_one_side": true,
      "mode_order_type": 0,
      "votes": [],
      "conf_id": 2004,
      "camp": 1
    },
    {
      "operate_type": 0,
      "battle_side": 1,
      "hero_id": 1029,
      "round_index": 2,
      "ban_pick_num": 1,
      "is_only_one_side": true,
      "mode_order_type": 0,
      "votes": [],
      "conf_id": 2004,
      "camp": 2
    },
    {
      "operate_type": 1,
      "battle_side": 1,
      "hero_id": 1024,
      "round_index": 3,
      "ban_pick_num": 1,
      "is_only_one_side": true,
      "mode_order_type": 0,
      "votes": [],
      "conf_id": 2004,
      "camp": 2
    },
    {
      "operate_type": 0,
      "battle_side": 0,
      "hero_id": 1036,
      "round_index": 4,
      "ban_pick_num": 1,
      "is_only_one_side": true,
      "mode_order_type": 0,
      "votes": [],
      "conf_id": 2004,
      "camp": 1
    },
    {
      "operate_type": 0,
      "battle_side": 1,
      "hero_id": 1034,
      "round_index": 5,
      "ban_pick_num": 1,
      "is_only_one_side": true,
      "mode_order_type": 1,
      "votes": [],
      "conf_id": 2004,
      "camp": 2
    },
    {
      "operate_type": 0,
      "battle_side": 0,
      "hero_id": 1038,
      "round_index": 5,
      "ban_pick_num": 1,
      "is_only_one_side": true,
      "mode_order_type": 1,
      "votes": [],
      "conf_id": 2004,
      "camp": 1
    },
    {
      "operate_type": 1,
      "battle_side": 1,
      "hero_id": 1029,
      "round_index": 6,
      "ban_pick_num": 1,
      "is_only_one_side": true,
      "mode_order_type": 0,
      "votes": [],
      "conf_id": 2004,
      "camp": 2
    },
    {
      "operate_type": 0,
      "battle_side": 0,
      "hero_id": 1045,
      "round_index": 7,
      "ban_pick_num": 1,
      "is_only_one_side": true,
      "mode_order_type": 0,
      "votes": [],
      "conf_id": 2004,
      "camp": 1
    },
    {
      "operate_type": 1,
      "battle_side": 0,
      "hero_id": 1026,
      "round_index": 8,
      "ban_pick_num": 1,
      "is_only_one_side": true,
      "mode_order_type": 0,
      "votes": [],
      "conf_id": 2004,
      "camp": 1
    },
    {
      "operate_type": 0,
      "battle_side": 1,
      "hero_id": 1056,
      "round_index": 9,
      "ban_pick_num": 1,
      "is_only_one_side": true,
      "mode_order_type": 0,
      "votes": [],
      "conf_id": 2004,
      "camp": 2
    }
  ]
}
